.coveragerc
.gitlab-ci.yml
AUTHORS
ChangeLog
LICENSE
README.rst
requirements.txt
setup.cfg
setup.py
test-requirements.txt
tox.ini
confspirator/__init__.py
confspirator/base.py
confspirator/constants.py
confspirator/example.py
confspirator/exceptions.py
confspirator/fields.py
confspirator/groups.py
confspirator/loader.py
confspirator/types.py
confspirator/utils.py
confspirator.egg-info/PKG-INFO
confspirator.egg-info/SOURCES.txt
confspirator.egg-info/dependency_links.txt
confspirator.egg-info/not-zip-safe
confspirator.egg-info/pbr.json
confspirator.egg-info/requires.txt
confspirator.egg-info/top_level.txt
confspirator/tests/__init__.py
confspirator/tests/test_configs.py
confspirator/tests/test_example.py
confspirator/tests/test_utils.py
confspirator/tests/utils.py
docs/Makefile
docs/make.bat
docs/requirements.txt
docs/source/advanced_usage.rst
docs/source/conf.py
docs/source/config_fields.rst
docs/source/generated_config.rst
docs/source/index.rst
docs/source/quick_start.rst
docs/source/test_utils.rst