Metadata-Version: 2.1
Name: confspirator
Version: 0.2.0
Summary: A config library for handling nested incode config groups.
Home-page: https://gitlab.com/catalyst-cloud/confspirator
Author: Adrian Turjak
Author-email: adriant@catalyst.net.nz
License: Apache-2
Project-URL: Bug Tracker, https://gitlab.com/catalyst-cloud/confspirator/issues
Project-URL: Source Code, https://gitlab.com/catalyst-cloud/confspirator
Keywords: configuration,config,yaml,nesting,nested,groups,grouped,group,in-code
Platform: UNKNOWN
Classifier: Development Status :: 5 - Production/Stable
Classifier: Intended Audience :: Developers
Classifier: Intended Audience :: System Administrators
Classifier: License :: OSI Approved :: Apache Software License
Classifier: Programming Language :: Python :: 3.6
Classifier: Programming Language :: Python :: 3.7
Classifier: Programming Language :: Python :: 3.8
Classifier: Environment :: OpenStack
